mosaictools/__init__.py
mosaictools/distributions.py
mosaictools/gpc_functions.py
mosaictools/gpc_surrogate.py
mosaictools/main.py
mosaictools/multiindex.py
mosaictools/polysys.py
mosaictools/simparameter.py
mosaictools/simparameter_set.py
mosaictools-0.1.11.dist-info/licenses/LICENSE
mosaictools-0.1.11.dist-info/METADATA
mosaictools-0.1.11.dist-info/WHEEL
mosaictools-0.1.11.dist-info/top_level.txt
mosaictools-0.1.11.dist-info/RECORD
