Metadata-Version: 2.4
Name: mosaictools
Version: 0.1.11
Summary: Surrogate modelling of modal properties using MOSAIC method
Home-page: https://github.com/blazkurent/mosaictools/
Author: Blaž Kurent
Author-email: blaz.kurent@fgg.uni-lj.si
Classifier: Programming Language :: Python :: 3
Classifier: License :: OSI Approved :: MIT License
Classifier: Operating System :: OS Independent
Classifier: Development Status :: 3 - Alpha
License-File: LICENSE
Requires-Dist: numpy
Requires-Dist: scikit-learn
Requires-Dist: scipy
Dynamic: author
Dynamic: author-email
Dynamic: classifier
Dynamic: description
Dynamic: description-content-type
Dynamic: home-page
Dynamic: license-file
Dynamic: requires-dist
Dynamic: summary
